stampix/auspostgen/__init__.py
stampix/auspostgen/generator.py
stampix/auspostgen/_c/CMakeLists.txt
stampix/auspostgen/_c/auspost.so
stampix/auspostgen/_c/auspost.c
stampix_auspostgen-0.0.13.dist-info/RECORD
stampix_auspostgen-0.0.13.dist-info/WHEEL
stampix_auspostgen-0.0.13.dist-info/METADATA
stampix_auspostgen-0.0.13.dist-info/licenses/LICENCE.txt
