Metadata-Version: 2.2
Name: stampix-auspostgen
Version: 0.0.13
Summary: Generation of the Australia Post Barcode versions 37, 52, 67
Author-Email: Damian Dennis <damiandennis@gmail.com>, Jaro Robberechts <jaro@stampix.com>
License: MIT
Classifier: Programming Language :: Python :: 3
Classifier: Operating System :: OS Independent
Requires-Python: >=3.10
